{"graphs": [{"id": "172768411205655", "nodes": [{"name": "axi_axil_adapter", "id": "node_172768411205610", "instanceName": "axi_bridge", "twoColumn": true, "interfaces": [{"name": "clk", "id": "ni_17276841120566", "direction": "input", "side": "left"}, {"name": "rst", "id": "ni_17276841120567", "direction": "input", "side": "left"}, {"name": "s_axi", "id": "ni_17276841120568", "direction": "input", "side": "left"}, {"name": "m_axi", "id": "ni_17276841120569", "direction": "output", "side": "right"}], "properties": [{"name": "ADDR_WIDTH", "id": "17276841120560", "value": "32"}, {"name": "AXI_DATA_WIDTH", "id": "17276841120561", "value": "32"}, {"name": "AXI_ID_WIDTH", "id": "17276841120562", "value": "12"}, {"name": "AXI_STRB_WIDTH", "id": "17276841120563", "value": "AXI_DATA_WIDTH/8"}, {"name": "AXIL_DATA_WIDTH", "id": "17276841120564", "value": "32"}, {"name": "AXIL_STRB_WIDTH", "id": "17276841120565", "value": "AXIL_DATA_WIDTH/8"}]}, {"name": "litex_pwm", "id": "node_172768411205615", "instanceName": "litex_pwm_top", "twoColumn": true, "interfaces": [{"name": "pwm", "id": "ni_172768411205611", "direction": "output", "side": "right"}, {"name": "sys_rst", "id": "ni_172768411205612", "direction": "input", "side": "left"}, {"name": "sys_clk", "id": "ni_172768411205613", "direction": "input", "side": "left"}, {"name": "s_axi", "id": "ni_172768411205614", "direction": "input", "side": "left"}], "properties": []}, {"name": "ps7", "id": "node_172768411205621", "instanceName": "ps7", "twoColumn": true, "interfaces": [{"name": "FCLK_RESET0_N", "id": "ni_172768411205616", "direction": "output", "side": "right"}, {"name": "MAXIGP0ARESETN", "id": "ni_172768411205617", "direction": "output", "side": "right"}, {"name": "MAXIGP0ACLK", "id": "ni_172768411205618", "direction": "input", "side": "left"}, {"name": "FCLK0", "id": "ni_172768411205619", "direction": "output", "side": "right"}, {"name": "M_AXI_GP0", "id": "ni_172768411205620", "direction": "output", "side": "right"}], "properties": []}, {"name": "External Output", "id": "node_172768411205624", "instanceName": "External Output", "twoColumn": true, "interfaces": [{"name": "external", "id": "ni_172768411205623", "direction": "input", "side": "left"}], "properties": [{"name": "External Name", "id": "172768411205622", "value": "pwm"}]}], "connections": [{"id": "172768411205647", "from": "ni_172768411205619", "to": "ni_17276841120566"}, {"id": "172768411205648", "from": "ni_172768411205616", "to": "ni_17276841120567"}, {"id": "172768411205649", "from": "ni_172768411205619", "to": "ni_172768411205613"}, {"id": "172768411205650", "from": "ni_172768411205616", "to": "ni_172768411205612"}, {"id": "172768411205651", "from": "ni_172768411205619", "to": "ni_172768411205618"}, {"id": "172768411205652", "from": "ni_172768411205620", "to": "ni_17276841120568"}, {"id": "172768411205653", "from": "ni_17276841120569", "to": "ni_172768411205614"}, {"id": "172768411205654", "from": "ni_172768411205611", "to": "ni_172768411205623"}]}], "entryGraph": "172768411205655", "version": "20240723.13"}